ryaml-0.4.0.dist-info/METADATA
ryaml-0.4.0.dist-info/WHEEL
ryaml/__init__.py
ryaml/py.typed
ryaml/__init__.pyi
ryaml/ryaml.abi3.so
ryaml-0.4.0.dist-info/RECORD
