Metadata-Version: 2.1
Name: ryaml
Version: 0.4.0
Classifier: Programming Language :: Python
Classifier: Programming Language :: Rust
Classifier: Programming Language :: Python :: 3.7
Classifier: Programming Language :: Python :: 3.8
Classifier: Programming Language :: Python :: 3.9
Classifier: Programming Language :: Python :: 3.10
Classifier: Development Status :: 3 - Alpha
Classifier: Operating System :: Microsoft :: Windows
Classifier: Operating System :: POSIX :: Linux
Classifier: Operating System :: MacOS
Classifier: Typing :: Typed
Summary: A simple yaml serializer and deserializer using Rust.
Keywords: 
Author: Ethan Smith <ethan@ethanhs.me>
Author-email: Ethan Smith <ethan@ethanhs.me>
Maintainer-email: Ethan Smith <ethan@ethanhs.me>
License: MIT
Requires-Python: >=3.7,<4
Project-URL: homepage, https://github.com/ethanhs/ryaml
Project-URL: repository, https://github.com/ethanhs/ryaml
